{
  "Productos": [
    {
      "idProducto": 1,
      "Nombre": "Tracy Vick",
      "Tipo": "Consumible",
      "PVenta": 14.6766,
      "PCoste": 9.0802,
      "Codigo": "Love",
      "Proveedor": "franklin@carter.pk",
      "Stock": 7,
      "Estatus": "Activo",
      "FCreacion": "2019-10-03",
      "FModificacion": "2019-10-03",
      "User": "Cesar"
    },
    {
      "idProducto": 2,
      "Nombre": "Natalie Stuart",
      "Tipo": "Consumible",
      "PVenta": 13.0837,
      "PCoste": 8.7879,
      "Codigo": "Atkins",
      "Proveedor": "kara@alston.ml",
      "Stock": 10,
      "Estatus": "Activo",
      "FCreacion": "2019-10-03",
      "FModificacion": "2019-10-03",
      "User": "Cesar"
    },
    {
      "idProducto": 3,
      "Nombre": "Eva Sherrill",
      "Tipo": "Consumible",
      "PVenta": 16.4787,
      "PCoste": 9.8712,
      "Codigo": "Clements",
      "Proveedor": "carol@burgess.tg",
      "Stock": 1,
      "Estatus": "Activo",
      "FCreacion": "2019-10-03",
      "FModificacion": "2019-10-03",
      "User": "Cesar"
    },
    {
      "idProducto": 4,
      "Nombre": "Hazel Alexander",
      "Tipo": "Consumible",
      "PVenta": 12.181,
      "PCoste": 8.3674,
      "Codigo": "McConnell",
      "Proveedor": "regina@boykin.ml",
      "Stock": 0,
      "Estatus": "Activo",
      "FCreacion": "2019-10-03",
      "FModificacion": "2019-10-03",
      "User": "Cesar"
    },
    {
      "idProducto": 5,
      "Nombre": "Gayle Floyd",
      "Tipo": "Consumible",
      "PVenta": 14.4915,
      "PCoste": 8.31,
      "Codigo": "Francis",
      "Proveedor": "vickie@schroeder.bn",
      "Stock": 10,
      "Estatus": "Activo",
      "FCreacion": "2019-10-03",
      "FModificacion": "2019-10-03",
      "User": "Cesar"
    },
    {
      "idProducto": 6,
      "Nombre": "Gayle Floyd",
      "Tipo": "Consumible",
      "PVenta": 14.4915,
      "PCoste": 8.31,
      "Codigo": "Francis",
      "Proveedor": "vickie@schroeder.bn",
      "Stock": 10,
      "Estatus": "Activo",
      "FCreacion": "2019-10-03",
      "FModificacion": "2019-10-03",
      "User": "Cesar"
    },
    {
      "idProducto": 7,
      "Nombre": "Gayle Floyd",
      "Tipo": "Consumible",
      "PVenta": 14.4915,
      "PCoste": 8.31,
      "Codigo": "Francis",
      "Proveedor": "vickie@schroeder.bn",
      "Stock": 10,
      "Estatus": "Activo",
      "FCreacion": "2019-10-03",
      "FModificacion": "2019-10-03",
      "User": "Cesar"
    },
    {
      "idProducto": 8,
      "Nombre": "Gayle Floyd",
      "Tipo": "Consumible",
      "PVenta": 14.4915,
      "PCoste": 8.31,
      "Codigo": "Francis",
      "Proveedor": "vickie@schroeder.bn",
      "Stock": 10,
      "Estatus": "Activo",
      "FCreacion": "2019-10-03",
      "FModificacion": "2019-10-03",
      "User": "Cesar"
    },
    {
      "idProducto": 9,
      "Nombre": "Gayle Floyd",
      "Tipo": "Consumible",
      "PVenta": 14.4915,
      "PCoste": 8.31,
      "Codigo": "Francis",
      "Proveedor": "vickie@schroeder.bn",
      "Stock": 10,
      "Estatus": "Activo",
      "FCreacion": "2019-10-03",
      "FModificacion": "2019-10-03",
      "User": "Cesar"
    },
    {
      "idProducto": 10,
      "Nombre": "Gayle Floyd",
      "Tipo": "Consumible",
      "PVenta": 14.4915,
      "PCoste": 8.31,
      "Codigo": "Francis",
      "Proveedor": "vickie@schroeder.bn",
      "Stock": 10,
      "Estatus": "Activo",
      "FCreacion": "2019-10-03",
      "FModificacion": "2019-10-03",
      "User": "Cesar"
    },
    {
      "idProducto": 11,
      "Nombre": "Gayle Floyd",
      "Tipo": "Consumible",
      "PVenta": 14.4915,
      "PCoste": 8.31,
      "Codigo": "Francis",
      "Proveedor": "vickie@schroeder.bn",
      "Stock": 10,
      "Estatus": "Activo",
      "FCreacion": "2019-10-03",
      "FModificacion": "2019-10-03",
      "User": "Cesar"
    },
    {
      "idProducto": 12,
      "Nombre": "Gayle Floyd",
      "Tipo": "Consumible",
      "PVenta": 14.4915,
      "PCoste": 8.31,
      "Codigo": "Francis",
      "Proveedor": "vickie@schroeder.bn",
      "Stock": 10,
      "Estatus": "Activo",
      "FCreacion": "2019-10-03",
      "FModificacion": "2019-10-03",
      "User": "Cesar"
    },
    {
      "idProducto": 13,
      "Nombre": "Gayle Floyd",
      "Tipo": "Consumible",
      "PVenta": 14.4915,
      "PCoste": 8.31,
      "Codigo": "Francis",
      "Proveedor": "vickie@schroeder.bn",
      "Stock": 10,
      "Estatus": "Activo",
      "FCreacion": "2019-10-03",
      "FModificacion": "2019-10-03",
      "User": "Cesar"
    },
    {
      "idProducto": 14,
      "Nombre": "Gayle Floyd",
      "Tipo": "Consumible",
      "PVenta": 14.4915,
      "PCoste": 8.31,
      "Codigo": "Francis",
      "Proveedor": "vickie@schroeder.bn",
      "Stock": 10,
      "Estatus": "Activo",
      "FCreacion": "2019-10-03",
      "FModificacion": "2019-10-03",
      "User": "Cesar"
    },
    {
      "idProducto": 15,
      "Nombre": "Gayle Floyd",
      "Tipo": "Consumible",
      "PVenta": 14.4915,
      "PCoste": 8.31,
      "Codigo": "Francis",
      "Proveedor": "vickie@schroeder.bn",
      "Stock": 10,
      "Estatus": "Activo",
      "FCreacion": "2019-10-03",
      "FModificacion": "2019-10-03",
      "User": "Cesar"
    }
  ],
  "Reglas": [
    {
      "idRegla": 1,
      "Nombre": "Kevin Hewitt",
      "idProducto": 1,
      "CantidadMin": 7.9335,
      "CantidadMax": 47.4501,
      "FCreacion": "2019-10-03",
      "FModificacion": "2019-10-03",
      "User": "Cesar"
    },
    {
      "idRegla": 2,
      "Nombre": "Jennifer Singleton",
      "idProducto": 2,
      "CantidadMin": 9.1201,
      "CantidadMax": 21.3855,
      "FCreacion": "2019-10-03",
      "FModificacion": "2019-10-03",
      "User": "Cesar"
    },
    {
      "idRegla": 3,
      "Nombre": "Marion Barr",
      "idProducto": 3,
      "CantidadMin": 9.0701,
      "CantidadMax": 44.473,
      "FCreacion": "2019-10-03",
      "FModificacion": "2019-10-03",
      "User": "Cesar"
    },
    {
      "idRegla": 4,
      "Nombre": "Neal Finch",
      "idProducto": 4,
      "CantidadMin": 9.2918,
      "CantidadMax": 30.3569,
      "FCreacion": "2019-10-03",
      "FModificacion": "2019-10-03",
      "User": "Cesar"
    },
    {
      "idRegla": 5,
      "Nombre": "Diana Beck",
      "idProducto": 5,
      "CantidadMin": 8.9041,
      "CantidadMax": 42.8234,
      "FCreacion": "2019-10-03",
      "FModificacion": "2019-10-03",
      "User": "Cesar"
    },
    {
      "idRegla": 6,
      "Nombre": "Diana Beck",
      "idProducto": 5,
      "CantidadMin": 8.9041,
      "CantidadMax": 42.8234,
      "FCreacion": "2019-10-03",
      "FModificacion": "2019-10-03",
      "User": "Cesar"
    },
    {
      "idRegla": 7,
      "Nombre": "Diana Beck",
      "idProducto": 5,
      "CantidadMin": 8.9041,
      "CantidadMax": 42.8234,
      "FCreacion": "2019-10-03",
      "FModificacion": "2019-10-03",
      "User": "Cesar"
    },
    {
      "idRegla": 8,
      "Nombre": "Diana Beck",
      "idProducto": 5,
      "CantidadMin": 8.9041,
      "CantidadMax": 42.8234,
      "FCreacion": "2019-10-03",
      "FModificacion": "2019-10-03",
      "User": "Cesar"
    },
    {
     "idRegla": 9,
      "Nombre": "Diana Beck",
      "idProducto": 5,
      "CantidadMin": 8.9041,
      "CantidadMax": 42.8234,
      "FCreacion": "2019-10-03",
      "FModificacion": "2019-10-03",
      "User": "Cesar"
    },
    {
      "idRegla": 10,
      "Nombre": "Diana Beck",
      "idProducto": 5,
      "CantidadMin": 8.9041,
      "CantidadMax": 42.8234,
      "FCreacion": "2019-10-03",
      "FModificacion": "2019-10-03",
      "User": "Cesar"
    },
    {
      "idRegla": 11,
      "Nombre": "Diana Beck",
      "idProducto": 5,
      "CantidadMin": 8.9041,
      "CantidadMax": 42.8234,
      "FCreacion": "2019-10-03",
      "FModificacion": "2019-10-03",
      "User": "Cesar"
    },
    {
      "idRegla": 12,
      "Nombre": "Diana Beck",
      "idProducto": 5,
      "CantidadMin": 8.9041,
      "CantidadMax": 42.8234,
      "FCreacion": "2019-10-03",
      "FModificacion": "2019-10-03",
      "User": "Cesar"
    },
    {
      "idRegla": 13,
      "Nombre": "Diana Beck",
      "idProducto": 5,
      "CantidadMin": 8.9041,
      "CantidadMax": 42.8234,
      "FCreacion": "2019-10-03",
      "FModificacion": "2019-10-03",
      "User": "Cesar"
    },
    {
      "idRegla": 14,
      "Nombre": "Diana Beck",
      "idProducto": 5,
      "CantidadMin": 8.9041,
      "CantidadMax": 42.8234,
      "FCreacion": "2019-10-03",
      "FModificacion": "2019-10-03",
      "User": "Cesar"
    },
    {
      "idRegla": 15,
      "Nombre": "Diana Beck",
      "idProducto": 5,
      "CantidadMin": 8.9041,
      "CantidadMax": 42.8234,
      "FCreacion": "2019-10-03",
      "FModificacion": "2019-10-03",
      "User": "Cesar"
    }
  ],
  "tarjeta": [
    {
      "id": 1,
      "Nombre": "hello",
	  "Tipo": "hello",
	  "Codigo": "hello",
	  "Desc": "hello",
	  "Precio": "3123",
	  "Inventario": "hello",
	   "img":"https://d500.epimg.net/cincodias/imagenes/2016/07/04/lifestyle/1467646262_522853_1467646344_noticia_normal.jpg"
    },
	 {
      "id": 2,
      "Nombre": "hello",
	  "Tipo": "hel",
	  "Codigo": "hel",
	  "Desc": "hel",
	  "Precio": "31231231",
	  "Inventario": "hel",
	  "img":"https://d500.epimg.net/cincodias/imagenes/2016/07/04/lifestyle/1467646262_522853_1467646344_noticia_normal.jpg"
	  
    },
	 {
      "id": 3,
      "Nombre": "helloasasd",
	  "Tipo": "helloasdasd",
	  "Codigo": "helloasdasda",
	  "Desc": "hello213123",
	  "Precio": "3123asdasd",
	  "Inventario": "hello12331asd",
	  "img":"https://d500.epimg.net/cincodias/imagenes/2016/07/04/lifestyle/1467646262_522853_1467646344_noticia_normal.jpg"
	  
	  
    },
	 {
      "id": 4,
      "Nombre": "hello1234",
	  "Tipo": "hell434o",
	  "Codigo": "hello3434",
	  "Desc": "hello434",
	  "Precio": "3123434",
	  "Inventario": "hello434434",
	  "img":"https://d500.epimg.net/cincodias/imagenes/2016/07/04/lifestyle/1467646262_522853_1467646344_noticia_normal.jpg"
	  
    }
  ]
}
